mitypes/__init__.py
mitypes/channel.py
mitypes/drive.py
mitypes/note.py
mitypes/poll.py
mitypes/user.py
mitypes-0.1.1.dist-info/METADATA
mitypes-0.1.1.dist-info/WHEEL
mitypes-0.1.1.dist-info/RECORD
