Metadata-Version: 2.1
Name: mitypes
Version: 0.1.1
Summary: Type definitions used in Misskey API responses.
Home-page: https://github.com/sonyakun/MisskeyTypes
License: MIT
Keywords: misskey,misskey-api,type-definitions
Author: sonyakun
Author-email: owner@sonyakun.com
Requires-Python: >=3.8,<4.0
Classifier: License :: OSI Approved :: MIT License
Classifier: Programming Language :: Python
Classifier: Programming Language :: Python :: 3
Classifier: Programming Language :: Python :: 3.8
Classifier: Programming Language :: Python :: 3.9
Classifier: Programming Language :: Python :: 3.10
Classifier: Programming Language :: Python :: 3.11
Classifier: Programming Language :: Python :: 3.12
Classifier: Programming Language :: Python :: 3 :: Only
Classifier: Topic :: Software Development :: Libraries :: Python Modules
Requires-Dist: pydantic (>=2.6.4,<3.0.0)
Project-URL: Repository, https://github.com/sonyakun/MisskeyTypes
